float_mul/float_mul.v

//TODO:
//1. accuracy improvment
//2. overflow,undeflow
//3. addition

module float_mul ( input [31:0] ain,input [31:0] bin, output [31:0] out);

wire [31:0] ZERO = 32'b0;
wire [31:0] NEGZERO = 32'h80000000;
wire zeroes = (ZERO==ain)||(ZERO==bin)||(NEGZERO==ain)||(NEGZERO==bin);
wire z_sign;
wire [7:0] z_exp;
wire [22:0] z_mat;
wire [63:0] mantissa_64_mult;

wire [8:0] exp_a,exp_b;
assign exp_a=ain[30:23];
assign exp_b=bin[30:23];
assign z_sign = (ain[31] ^ bin[31]);
assign z_exp = (ain[30:23] + bin[30:23] - 8'd127) + norm_exp_value;

//assign mantissa_64_mult = man_norm_a * man_norm_b;
assign mantissa_64_mult = (({1'b1,ain[22:0]}) * ({1'b1,bin[22:0]})); 
//assign mantissa_48 = mantissa_48_mult[(post_zeros-1) -:23];
assign z_mat = mantissa_64_mult[post_zeros-24] ?  (mantissa_64_mult[(post_zeros-1) -:23] +1) : mantissa_64_mult[(post_zeros-1) -:23];

assign out = zeroes ? ZERO : {z_sign,z_exp,z_mat};

wire [5:0] a_width,b_width;
wire [23:0] man_norm_a,man_norm_b;
wire [5:0] sum_widths,mantissa_width;
wire [7:0] norm_exp_value;
assign man_norm_a = {1'b1,ain[22:0]}>> (n1);
assign man_norm_b = {1'b1,bin[22:0]}>> (n2);
assign a_width = m1-n1;
assign b_width = m2-n2;
assign sum_widths = (a_width + b_width); 
assign mantissa_width = post_zeros - trail_zeros;
//assign norm_exp_value = mantissa_width - sum_widths;
//assign norm_exp_value = (post_zeros > 46) ? (post_zeros - 8'd46) : 0;
assign norm_exp_value = mantissa_64_mult[47]; 



integer i;
reg [5:0] trail_zeros;
reg [5:0] post_zeros;
reg first,first_a,first_b;
reg [4:0] m1,n1,m2,n2;

//get trailing zeros
always @(*) begin
    trail_zeros = 0;
    post_zeros = 0;
    first = 0;
    first_a = 0;
    first_b = 0;
    n1 =0;
    m1 =0;
    n2 =0;
    m2 =0;
    for(i=1;i<63;i=i+1) begin
        if((mantissa_64_mult[i-1]==1'b0) && (mantissa_64_mult[i]==1'b1) && ~first) begin 
            trail_zeros = i;
            first = 1;
            //$display ("mantissa[i-1]= %b , mantissa[i]= %b, i= %d, first=%b, mantissa_64_mult=%b",  mantissa_64_mult[i-1],mantissa_64_mult[i],i,first,mantissa_64_mult);
        end
        
        if((mantissa_64_mult[i-1]==1'b1) && (mantissa_64_mult[i]==1'b0)) begin 
            post_zeros = i-1;
            //$display ("mantissa[i-1]= %b , mantissa[i]= %b, i= %d, mantissa_64_mult=%b",  mantissa_64_mult[i-1],mantissa_64_mult[i],i,mantissa_64_mult);
        end
    end

    for(i=1;i<24;i=i+1) begin
        if((ain[i-1]==0) && (ain[i]==1) && first_a == 0) begin
            n1 = i;
            first_a = 1;
        end
        if((ain[i-1]==1) && (ain[i]==0)) m1 = i-1;

        if((bin[i-1]==0) && (bin[i]==1) && first_b == 0) begin
            n2 = i;
            first_b = 1;
        end
        if((bin[i-1]==1) && (bin[i]==0)) m2 = i-1;

    end

end

//$display("ain exp = %b ", ain[30:23]);
//$display("bin exp = %d ",bin[30:23]);

endmodule

float_mul/tb.v
module tb;
reg [31:0] cycles;   initial cycles=0;
reg [31:0] errors;   initial errors=0;
reg [31:0] wrongs;   initial wrongs=0;
reg [31:0] corrects; initial corrects=0;
reg [31:0] marker;   initial marker=0;


reg  clk;
always begin
    clk=0;
    #10;
    clk=1;
    #3;
    $python("negedge()");
    #7;
end

initial begin
    $dumpvars(0,tb);
    ain = 0;
    bin = 0;
    #100;
end

reg [31:0] ain;
reg [31:0] bin;
wire [31:0] out;

float_mul dut (
    .ain(ain),
    .bin(bin),
    .out(out)

);


endmodule

float_mul/dump.vcd
$date
	Sun Nov 24 14:38:33 2024
$end
$version
	Icarus Verilog
$end
$timescale
	1s
$end
$scope module tb $end
$var wire 32 ! out [31:0] $end
$var reg 32 " ain [31:0] $end
$var reg 32 # bin [31:0] $end
$var reg 1 $ clk $end
$var reg 32 % corrects [31:0] $end
$var reg 32 & cycles [31:0] $end
$var reg 32 ' errors [31:0] $end
$var reg 32 ( marker [31:0] $end
$var reg 32 ) wrongs [31:0] $end
$scope module dut $end
$var wire 32 * NEGZERO [31:0] $end
$var wire 32 + ZERO [31:0] $end
$var wire 32 , ain [31:0] $end
$var wire 32 - bin [31:0] $end
$var wire 1 . z_sign $end
$var wire 1 / zeroes $end
$var wire 23 0 z_mat [22:0] $end
$var wire 8 1 z_exp [7:0] $end
$var wire 6 2 sum_widths [5:0] $end
$var wire 32 3 out [31:0] $end
$var wire 8 4 norm_exp_value [7:0] $end
$var wire 6 5 mantissa_width [5:0] $end
$var wire 64 6 mantissa_64_mult [63:0] $end
$var wire 24 7 man_norm_b [23:0] $end
$var wire 24 8 man_norm_a [23:0] $end
$var wire 9 9 exp_b [8:0] $end
$var wire 9 : exp_a [8:0] $end
$var wire 6 ; b_width [5:0] $end
$var wire 6 < a_width [5:0] $end
$var reg 1 = first $end
$var reg 1 > first_a $end
$var reg 1 ? first_b $end
$var reg 5 @ m1 [4:0] $end
$var reg 5 A m2 [4:0] $end
$var reg 5 B n1 [4:0] $end
$var reg 5 C n2 [4:0] $end
$var reg 6 D post_zeros [5:0] $end
$var reg 6 E trail_zeros [5:0] $end
$var integer 32 F i [31:0] $end
$upscope $end
$upscope $end
$enddefinitions $end
#0
$dumpvars
b11000 F
b101110 E
b101110 D
b0 C
b0 B
b0 A
b0 @
0?
0>
1=
b0 <
b0 ;
b0 :
b0 9
b100000000000000000000000 8
b100000000000000000000000 7
b10000000000000000000000000000000000000000000000 6
b0 5
b0 4
b0 3
b0 2
b10000001 1
b0 0
1/
0.
b0 -
b0 ,
b0 +
b10000000000000000000000000000000 *
b0 )
b0 (
b0 '
b0 &
b0 %
0$
b0 #
b0 "
b0 !
$end
#10
1$
#13
b1000100100000001101111001000011 !
b1000100100000001101111001000011 3
0/
b1 4
b1101111001000011 0
b10000011 9
1>
b101 B
b10101 A
b10000 <
b10101 @
1?
b1011100110011000011101 7
b100011 2
b10011 ;
b10 C
b11000 F
1=
b101111 D
b101011 5
b100 E
b10000100 :
b10001001 1
b100000001101111001000010101101010101000110010011 6
b1011000111000000111 8
b1000001101110011001100001110101 #
b1000001101110011001100001110101 -
b1000010001100011100000011100111 "
b1000010001100011100000011100111 ,
b1 &
#20
0$
#30
1$
#33
b1 %
b10 &
#40
0$
#50
1$
#53
b0 4
b1000100111000111001000011110000 !
b1000100111000111001000011110000 3
b11000111001000011110000 0
b11000 F
b10101 A
b10100010110110101110011 7
b10100 ;
b1 C
b10101 @
b101000 2
b10100 <
b1 B
1?
1>
1=
b101110 D
b101100 5
b10 E
b10000101 :
b10001001 1
b11100011100100001111000001100010110010100110100 6
b10110010110111000111111 8
b1000001101000101101101011100110 #
b1000001101000101101101011100110 -
b1000010101100101101110001111110 "
b1000010101100101101110001111110 ,
b11 &
#60
0$
#70
1$
#73
b10 %
b100 &
#80
0$
#90
1$
#93
b1000101000011111100110110101101 !
b1000101000011111100110110101101 3
b11111100110110101101 0
b1 4
b10000100 9
b11000 F
b10101 A
b101000101010001001001 7
b10010 ;
b11 C
b10110 @
b100111 2
b10101 <
b1 B
1?
1>
1=
b101111 D
b101110 5
b1 E
b10000100 :
b10001010 1
b100011111100110110101101000110011000101010111010 6
b11100010010110111110111 8
b1000010001000101010001001001011 #
b1000010001000101010001001001011 -
b1000010011000100101101111101110 "
b1000010011000100101101111101110 ,
b101 &
#100
0$
#110
1$
#113
b11 %
b110 &
#120
0$
#130
1$
#133
1.
b11000100010001101010111011000110 !
b11000100010001101010111011000110 3
b10001101010111011000110 0
b0 4
b10000010 9
b11000 F
b10100 A
b10011100100010110101 7
b10000 ;
b100 C
b10101 @
b100010 2
b10010 <
b11 B
1?
1>
1=
b101110 D
b101011 5
b11 E
b10000101 :
b10001000 1
b11000110101011101100011000010001110101011101000 6
b101000100111010001111 8
b11000001000111001000101101010011 #
b11000001000111001000101101010011 -
b1000010101000100111010001111000 "
b1000010101000100111010001111000 ,
b111 &
#140
0$
#150
1$
#153
b100 %
b1000 &
#160
0$
#170
1$
#173
b11000010001101111100111010000100 !
b11000010001101111100111010000100 3
b1101111100111010000100 0
b1111111 9
b11000 F
b10001 A
b100000110101101001001 7
b1110 ;
b11 C
b10101 @
b100001 2
b10011 <
b10 B
1?
1>
1=
b101110 D
b101100 5
b10 E
b10000100 :
b10000100 1
b10110111110011101000001111001010000000001011100 6
b1011001100011101011111 8
b10111111100000110101101001001001 #
b10111111100000110101101001001001 -
b1000010001100110001110101111100 "
b1000010001100110001110101111100 ,
b1001 &
#180
0$
#190
1$
#193
b101 %
b1010 &
#200
0$
#210
1$
#213
0.
b1000100001000001101010010111000 !
b1000100001000001101010010111000 3
b1 4
b1000001101010010111000 0
b10000010 9
b10001000 1
b11000 F
b10110 A
b111111111101111011111 7
b10011 ;
b11 C
b10101 @
b100101 2
b10010 <
b11 B
1?
1>
1=
b101111 D
b101010 5
b101 E
b101000001101010010110111110000101101011110100011 6
b101000001110100101111 8
b1000001011111111101111011111011 #
b1000001011111111101111011111011 -
b1000010001000001110100101111001 "
b1000010001000001110100101111001 ,
b1011 &
#220
0$
#230
1$
#233
b110 %
b1100 &
#240
0$
#250
1$
#253
b0 4
b1000101010001110111000100001011 !
b1000101010001110111000100001011 3
b10001110111000100001011 0
b10000100 9
b11000 F
b10100 A
b1001010001001100011 7
b1111 ;
b101 C
b10101 @
b100010 2
b10011 <
b10 B
1?
1>
1=
b101110 D
b101100 5
b10 E
b10000101 :
b10001010 1
b11000111011100010000101101011101010011110001100 6
b1010110000100100100101 8
b1000010000101000100110001100111 #
b1000010000101000100110001100111 -
b1000010101011000010010010010100 "
b1000010101011000010010010010100 ,
b1101 &
#260
0$
#270
1$
#273
b111 %
b1110 &
#280
0$
#290
1$
#293
1.
b11000011011110001110110000110000 !
b11000011011110001110110000110000 3
b11110001110110000110000 0
b10000000 9
b10000110 1
b11000 F
b10110 A
b1110110011011000111 7
b10001 ;
b101 C
b10010 @
b100001 2
b10000 <
b10 B
1?
1>
1=
b101110 D
b101100 5
b10 E
b11111000111011000010111111100111000111100000101 6
b1000011010000110101001 8
b11000000011011001101100011100001 #
b11000000011011001101100011100001 -
b1000010100001101000011010100101 "
b1000010100001101000011010100101 ,
b1111 &
#300
0$
#310
1$
#313
b1000 %
b10000 &
#320
0$
#330
1$
#333
0.
b1000101001100010100000010000010 !
b1000101001100010100000010000010 3
b1100010100000010000010 0
b10000100 9
b10001010 1
b11000 F
b10100 A
b1001000100010010011101 7
b10010 ;
b10 C
b10100 @
b100011 2
b10001 <
b11 B
1?
1>
1=
b101110 D
b101100 5
b10 E
b10110001010000001000001001101011011101111101101 6
b100111000110010010011 8
b1000010000100010001001001110101 #
b1000010000100010001001001110101 -
b1000010100111000110010010011001 "
b1000010100111000110010010011001 ,
b10001 &
#340
0$
#350
1$
#353
b1001 %
b10010 &
#360
0$
#370
1$
#373
b1000100101110111111110100000110 !
b1000100101110111111110100000110 3
b1110111111110100000110 0
b1 4
b10000011 9
b11000 F
b10010 A
b1100011010001011 7
b1010 ;
b1000 C
b10110 @
b11111 2
b10101 <
b1 B
1?
1>
1=
b101111 D
b101110 5
b1 E
b10000100 :
b10001001 1
b101110111111110100000110010011100101011000010110 6
b11110010011001000001011 8
b1000001110001101000101100000001 #
b1000001110001101000101100000001 -
b1000010011100100110010000010110 "
b1000010011100100110010000010110 ,
b10011 &
#380
0$
#390
1$
#393
b1010 %
b10100 &
#400
0$
#410
1$
#413
b1000011101100001011111111110100 !
b1000011101100001011111111110100 3
b1100001011111111110100 0
b10000001 9
b10000111 1
b11000 F
b10101 A
b101100010000011110011 7
b10010 ;
b11 C
b10110 @
b100111 2
b10101 <
b1 B
1?
1>
1=
b101111 D
b101110 5
b1 E
b101100001011111111110100011100101101111011110110 6
b11111111100110000110011 8
b1000000101100010000011110011001 #
b1000000101100010000011110011001 -
b1000010011111111001100001100110 "
b1000010011111111001100001100110 ,
b10101 &
#420
0$
#430
1$
#433
b1011 %
b10110 &
#440
0$
#450
1$
#453
b1000100000111011110000100100001 !
b1000100000111011110000100100001 3
b111011110000100100001 0
b0 4
b10000011 9
b10001000 1
b11000 F
b10100 A
b1001000001111001010011 7
b10010 ;
b10 C
b10011 @
b11110 2
b1100 <
b111 B
1?
1>
1=
b101110 D
b101100 5
b10 E
b10011101111000010010000010101001001000111100100 6
b10001011111000001 8
b1000001100100000111100101001100 #
b1000001100100000111100101001100 -
b1000010000010111110000010000011 "
b1000010000010111110000010000011 ,
b10111 &
#460
0$
#470
1$
#473
b1100 %
b11000 &
#480
0$
#490
1$
#493
b1 4
b1000010001000101011111010110001 !
b1000010001000101011111010110001 3
b1000101011111010110001 0
b10000001 9
b11000 F
b10100 A
b11011101111011101011001 7
b10011 ;
b1 C
b10101 @
b100101 2
b10010 <
b11 B
1?
1>
1=
b101111 D
b101110 5
b1 E
b10000001 :
b10000100 1
b101000101011111010110001000111111010001101100010 6
b101110111011101000011 8
b1000000110111011110111010110010 #
b1000000110111011110111010110010 -
b1000000101110111011101000011001 "
b1000000101110111011101000011001 ,
b11001 &
#500
0$
#510
1$
#513
b1101 %
b11010 &
#520
0$
#530
1$
#533
b1000100100010001100010100101000 !
b1000100100010001100010100101000 3
b10001100010100101000 0
b10000011 9
b11000 F
b10011 A
b1100110010011101001001 7
b10001 ;
b10 C
b10101 @
b100100 2
b10011 <
b10 B
1?
1>
1=
b101111 D
b101011 5
b100 E
b10000100 :
b10001001 1
b100010001100010100100111110011111111010110010000 6
b1010101100011110010001 8
b1000001110011001001110100100100 #
b1000001110011001001110100100100 -
b1000010001010110001111001000100 "
b1000010001010110001111001000100 ,
b11011 &
#540
0$
#550
1$
#553
b1110 %
b11100 &
#560
0$
#570
1$
#573
b1000000011010101010101001110000 !
b1000000011010101010101001110000 3
b11010101010101001110000 0
b0 4
b1111111 9
b11000 F
b10011 A
b110010101000100011011 7
b10000 ;
b11 C
b10100 @
b100011 2
b10011 <
b1 B
1?
1>
1=
b101110 D
b101101 5
b1 E
b10000000 :
b10000000 1
b11101010101010100110111111111100001010111001010 6
b10010100010011100111111 8
b111111110010101000100011011011 #
b111111110010101000100011011011 -
b1000000000101000100111001111110 "
b1000000000101000100111001111110 ,
b11101 &
#580
0$
#590
1$
#593
b1111 %
b11110 &
#600
0$
#610
1$
#613
1.
b11000100000010100101010100000110 !
b11000100000010100101010100000110 3
b10100101010100000110 0
b1 4
b10000101 9
b11000 F
b10100 A
b10011000010110111 7
b1101 ;
b111 C
b10011 @
b11111 2
b10010 <
b1 B
1?
1>
1=
b101111 D
b100111 5
b1000 E
b10000001 :
b10001000 1
b100010100101010100000110011000101110111100000000 6
b11101000011011110001001 8
b1000010100110000101101110000000 #
b1000010100110000101101110000000 -
b11000000111010000110111100010010 "
b11000000111010000110111100010010 ,
b11111 &
#620
0$
#630
1$
#633
b10000 %
b100000 &
#640
0$
#650
1$
#653
0.
b1000100101001110001010010100100 !
b1000100101001110001010010100100 3
b1001110001010010100100 0
b0 4
b10000100 9
b11000 F
b10100 A
b1001101100001011001101 7
b10010 ;
b10 C
b10011 @
b100011 2
b10001 <
b10 B
1?
1>
1=
b101110 D
b101010 5
b100 E
b10000100 :
b10001001 1
b10100111000101001010010000100000011100110010000 6
b1000100111101111111101 8
b1000010000110110000101100110100 #
b1000010000110110000101100110100 -
b1000010000010011110111111110100 "
b1000010000010011110111111110100 ,
b100001 &
#660
0$
#670
1$
#673
b10001 %
b100010 &
#680
0$
#690
1$
#693
b1000101101111100110011100111101 !
b1000101101111100110011100111101 3
b1111100110011100111101 0
b10000101 9
b11000 F
b10101 A
b10111010101111000111111 7
b10100 ;
b1 C
b10001 @
b100010 2
b1110 <
b11 B
1?
1>
1=
b101110 D
b101101 5
b1 E
b10000101 :
b10001011 1
b10111110011001110011110101100111001000110001110 6
b100000101000001101111 8
b1000010101110101011110001111110 #
b1000010101110101011110001111110 -
b1000010100000101000001101111001 "
b1000010100000101000001101111001 ,
b100011 &
#700
0$
#710
1$
#713
b10010 %
b100100 &
#720
0$
#730
1$
#733
b1000101011100111111111011111110 !
b1000101011100111111111011111110 3
b11100111111111011111110 0
b11000 F
b10101 A
b101100101001101111111 7
b10010 ;
b11 C
b10101 @
b100110 2
b10100 <
b1 B
1?
1>
1=
b101110 D
b101010 5
b100 E
b10000100 :
b10001010 1
b11110011111111101111111001100111110100000010000 6
b10101110110110111111111 8
b1000010101100101001101111111000 #
b1000010101100101001101111111000 -
b1000010001011101101101111111110 "
b1000010001011101101101111111110 ,
b100101 &
#740
0$
#750
1$
#753
b10011 %
b100110 &
#760
0$
#770
1$
#773
1.
b11000011010110011110100010011111 !
b11000011010110011110100010011111 3
b10110011110100010011111 0
b10000100 9
b11000 F
b10010 A
b10000101100001101011111 7
b10001 ;
b1 C
b10100 @
b100011 2
b10010 <
b10 B
1?
1>
1=
b101110 D
b101011 5
b11 E
b10000001 :
b10000110 1
b11011001111010001001111011011100000111101011000 6
b1101000011100011110101 8
b1000010000001011000011010111110 #
b1000010000001011000011010111110 -
b11000000110100001110001111010100 "
b11000000110100001110001111010100 ,
b100111 &
#780
0$
#790
1$
#793
b10100 %
b101000 &
#800
0$
#810
1$
#813
0.
b1000100101110000011010110111011 !
b1000100101110000011010110111011 3
b1110000011010110111011 0
b11000 F
b10101 A
b1010110101101010001 7
b10000 ;
b101 C
b10010 @
b100001 2
b10001 <
b1 B
1?
1>
1=
b101110 D
b101101 5
b1 E
b10000100 :
b10001001 1
b10111000001101011011101100010010010011011001110 6
b10000111111101111101101 8
b1000010001011010110101000100011 #
b1000010001011010110101000100011 -
b1000010000001111111011111011010 "
b1000010000001111111011111011010 ,
b101001 &
#820
0$
#830
1$
#833
b10101 %
b101010 &
#840
0$
#850
1$
#853
b1000101101001101000011000011000 !
b1000101101001101000011000011000 3
b1001101000011000011000 0
b1 4
b10000101 9
b10001011 1
b11000 F
b10101 A
b101010010100001100011 7
b10010 ;
b11 C
b10110 @
b100110 2
b10100 <
b10 B
1?
1>
1=
b101111 D
b101101 5
b10 E
b101001101000011000010111100000001100001000100100 6
b1111101111011011110001 8
b1000010101010010100001100011001 #
b1000010101010010100001100011001 -
b1000010011110111101101111000100 "
b1000010011110111101101111000100 ,
b101011 &
#860
0$
#870
1$
#873
b10110 %
b101100 &
#880
0$
#890
1$
#893
b1000101011010011001011110111100 !
b1000101011010011001011110111100 3
b10001010 1
b0 4
b11010011001011110111100 0
b11000 F
b10011 A
b100011000111010100101 7
b10000 ;
b11 C
b10110 @
b100001 2
b10001 <
b101 B
1?
1>
1=
b101110 D
b101001 5
b101 E
b11101001100101111011110001110000101101000100001 6
b1101010011011111111 8
b1000010100011000111010100101011 #
b1000010100011000111010100101011 -
b1000010010101001101111111100011 "
b1000010010101001101111111100011 ,
b101101 &
#900
0$
#910
1$
#913
b10111 %
b101110 &
#920
0$
#930
1$
#933
1.
b11000011010011010011011001101111 !
b11000011010011010011011001101111 3
b10011010011011001101111 0
b1 4
b10000011 9
b11000 F
b10011 A
b11001111010000111 7
b1100 ;
b111 C
b10000 @
b11000 2
b1100 <
b100 B
1?
1>
1=
b101111 D
b101011 5
b100 E
b10000001 :
b10000110 1
b110011010011011001101111011111000100110000010000 6
b11111101011101110111 8
b1000001110011110100001110000111 #
b1000001110011110100001110000111 -
b11000000111111010111011101110000 "
b11000000111111010111011101110000 ,
b101111 &
#940
0$
#950
1$
#953
b11000 %
b110000 &
#960
0$
#970
1$
#973
b0 4
0.
b1000011111101100001111011110010 !
b1000011111101100001111011110010 3
b11101100001111011110010 0
b11000 F
b10101 A
b1011001111001010101011 7
b10011 ;
b10 C
b10101 @
b100101 2
b10010 <
b11 B
1?
1>
1=
b101110 D
b101100 5
b10 E
b10000011 :
b10000111 1
b11110110000111101111000111111111010010010100101 6
b101011110011100011011 8
b1000001101100111100101010101101 #
b1000001101100111100101010101101 -
b1000001101011110011100011011001 "
b1000001101011110011100011011001 ,
b110001 &
#980
0$
#990
1$
#993
b11001 %
b110010 &
#1000
0$
#1010
1$
#1013
1.
b11000011100100100100001110000111 !
b11000011100100100100001110000111 3
b100100100001110000111 0
b1 4
b10000100 9
b11000 F
b10100 A
b100111101011011000101 7
b10001 ;
b11 C
b10011 @
b11010 2
b1001 <
b1010 B
1?
1>
1=
b101111 D
b100010 5
b1101 E
b10000001 :
b10000111 1
b100100100100001110000110101001001110000000000000 6
b11101011111011 8
b1000010000111101011011000101000 #
b1000010000111101011011000101000 -
b11000000111010111110110000000000 "
b11000000111010111110110000000000 ,
b110011 &
#1020
0$
#1030
1$
#1033
b11010 %
b110100 &
#1040
0$
#1050
1$
#1053
0.
b1000100110110001010110001111110 !
b1000100110110001010110001111110 3
b10110001010110001111110 0
b0 4
b10000101 9
b11000 F
b10010 A
b1100011011111 7
b111 ;
b1011 C
b10011 @
b11000 2
b10001 <
b10 B
1?
1>
1=
b101110 D
b101100 5
b10 E
b10000011 :
b10001001 1
b11011000101011000111111001110001100001111010100 6
b1000101101100011110101 8
b1000010110001101111100000000001 #
b1000010110001101111100000000001 -
b1000001100010110110001111010100 "
b1000001100010110110001111010100 ,
b110101 &
#1060
0$
#1070
1$
#1073
b11011 %
b110110 &
#1080
0$
#1090
1$
#1093
b1000011010111100010000101001101 !
b1000011010111100010000101001101 3
b10111100010000101001101 0
b10000100 9
b11000 F
b10101 A
b10111001001111001 7
b1110 ;
b111 C
b10100 @
b100000 2
b10010 <
b10 B
1?
1>
1=
b101110 D
b101011 5
b11 E
b10000001 :
b10000110 1
b11011110001000010100110010110100100011001101011 6
b1001100101111110011001 8
b1000010001110010011110010001111 #
b1000010001110010011110010001111 -
b1000000100110010111111001100101 "
b1000000100110010111111001100101 ,
b110111 &
#1100
0$
#1110
1$
#1113
b11100 %
b111000 &
#1120
0$
#1130
1$
#1133
b1 4
b1000100000001101010111011010000 !
b1000100000001101010111011010000 3
b1101010111011010000 0
b10000001 9
b11000 F
b10100 A
b1101001000111110010001 7
b10010 ;
b10 C
b10101 @
b100011 2
b10001 <
b100 B
1?
1>
1=
b101111 D
b101011 5
b100 E
b10000101 :
b10001000 1
b100001101010111011010000010000100100010101110000 6
b10100011111111101011 8
b1000000110100100011111001000101 #
b1000000110100100011111001000101 -
b1000010101000111111111010110000 "
b1000010101000111111111010110000 ,
b111001 &
#1140
0$
#1150
1$
#1153
b11101 %
b111010 &
#1160
0$
#1170
1$
#1173
b1000101011000001100001000011001 !
b1000101011000001100001000011001 3
b0 4
b11000001100001000011001 0
b10000100 9
b10001010 1
b11000 F
b10101 A
b101101100011101001111 7
b10010 ;
b11 C
b10100 @
b100001 2
b1111 <
b101 B
1?
1>
1=
b101110 D
b101001 5
b101 E
b11100000110000100001100010001001011000111100000 6
b1001110111011111101 8
b1000010001101100011101001111011 #
b1000010001101100011101001111011 -
b1000010100111011101111110100000 "
b1000010100111011101111110100000 ,
b111011 &
#1180
0$
#1190
1$
#1193
b11110 %
b111100 &
#1200
0$
#1210
1$
#1213
b1000011010111100100100101011011 !
b1000011010111100100100101011011 3
b10111100100100101011011 0
b10000001 9
b11000 F
b10100 A
b11010010001110011011001 7
b10011 ;
b1 C
b10010 @
b100011 2
b10000 <
b10 B
1?
1>
1=
b101110 D
b101011 5
b11 E
b10000100 :
b10000110 1
b11011110010010010101101011010100100100100111000 6
b1000011101010111111111 8
b1000000110100100011100110110010 #
b1000000110100100011100110110010 -
b1000010000001110101011111111100 "
b1000010000001110101011111111100 ,
b111101 &
#1220
0$
#1230
1$
#1233
b11111 %
b111110 &
#1240
0$
#1250
1$
#1253
b1000100001111100010000100101111 !
b1000100001111100010000100101111 3
b1111100010000100101111 0
b10000010 9
b11000 F
b10101 A
b10100111111101010010111 7
b10100 ;
b1 C
b10100 @
b100111 2
b10011 <
b1 B
1?
1>
1=
b101110 D
b101100 5
b10 E
b10000101 :
b10001000 1
b10111110001000010010111101110101111011010001100 6
b10010000111001011010101 8
b1000001001001111111010100101110 #
b1000001001001111111010100101110 -
b1000010100100001110010110101010 "
b1000010100100001110010110101010 ,
b111111 &
#1260
0$
#1270
1$
#1273
b100000 %
b1000000 &
#1280
0$
#1290
1$
#1293
b1000100101011111000001011111010 !
b1000100101011111000001011111010 3
b1011111000001011111010 0
b1 4
b10000011 9
b11000 F
b10101 A
b1011000110000111011011 7
b10011 ;
b10 C
b10110 @
b100011 2
b10000 <
b110 B
1?
1>
1=
b101111 D
b101101 5
b10 E
b10000100 :
b10001001 1
b101011111000001011111010001000110100001011110100 6
b111111010001011101 8
b1000001101100011000011101101100 #
b1000001101100011000011101101100 -
b1000010011111010001011101000111 "
b1000010011111010001011101000111 ,
b1000001 &
#1300
0$
#1310
1$
#1313
b100001 %
b1000010 &
#1320
0$
#1330
1$
#1333
b1000011010001110011010010100100 !
b1000011010001110011010010100100 3
b10001110011010010100100 0
b10000010 9
b11000 F
b10110 A
b1101000001101001101101 7
b10100 ;
b10 C
b10110 @
b101001 2
b10101 <
b1 B
1?
1>
1=
b101111 D
b101110 5
b1 E
b10000010 :
b10000110 1
b110001110011010010100011110111101110010001010110 6
b11110100101100001011111 8
b1000001010100000110100110110101 #
b1000001010100000110100110110101 -
b1000001011101001011000010111110 "
b1000001011101001011000010111110 ,
b1000011 &
#1340
0$
#1350
1$
#1353
b100010 %
b1000100 &
#1360
0$
#1370
1$
#1373
b1000010011100110111101111101111 !
b1000010011100110111101111101111 3
b11100110111101111101111 0
b0 4
b10000001 9
b10000100 1
b11000 F
b10001 A
b1110001000010011001011 7
b1111 ;
b10 C
b10011 @
b11111 2
b10000 <
b11 B
1?
1>
1=
b101110 D
b101100 5
b10 E
b11110011011110111110111100010110100111001001100 6
b100010011101101101011 8
b1000000111000100001001100101100 #
b1000000111000100001001100101100 -
b1000001000010011101101101011001 "
b1000001000010011101101101011001 ,
b1000101 &
#1380
0$
#1390
1$
#1393
b100011 %
b1000110 &
#1400
0$
#1410
1$
#1413
b1000100111111100110101110100111 !
b1000100111111100110101110100111 3
b11111100110101110100111 0
b10000101 9
b11000 F
b10101 A
b10111001101010100110111 7
b10100 ;
b1 C
b10101 @
b101000 2
b10100 <
b1 B
1?
1>
1=
b101110 D
b101100 5
b10 E
b10000011 :
b10001001 1
b11111110011010111010011100101010000110001101100 6
b10101111011001100111101 8
b1000010101110011010101001101110 #
b1000010101110011010101001101110 -
b1000001101011110110011001111010 "
b1000001101011110110011001111010 ,
b1000111 &
#1420
0$
#1430
1$
#1433
b100100 %
b1001000 &
#1440
0$
#1450
1$
#1453
b1000011011011011010001110101011 !
b1000011011011011010001110101011 3
b11011011010001110101011 0
b10000011 9
b11000 F
b10101 A
b10110010100110001011111 7
b10100 ;
b1 C
b10101 @
b100110 2
b10010 <
b11 B
1?
1>
1=
b101110 D
b101101 5
b1 E
b10000010 :
b10000110 1
b11101101101000111010101010010101101100100001110 6
b101010100101000011011 8
b1000001101100101001100010111110 #
b1000001101100101001100010111110 -
b1000001001010100101000011011001 "
b1000001001010100101000011011001 ,
b1001001 &
#1460
0$
#1470
1$
#1473
b100101 %
b1001010 &
#1480
0$
#1490
1$
#1493
b1000100110101011100111011111110 !
b1000100110101011100111011111110 3
b10101011100111011111110 0
b1 4
b10000100 9
b11000 F
b10110 A
b110111001011111111011 7
b10011 ;
b11 C
b10010 @
b100010 2
b1111 <
b11 B
1?
1>
1=
b101111 D
b101100 5
b11 E
b10000011 :
b10001001 1
b110101011100111011111110001001111110101100101000 6
b111101111111001101101 8
b1000010010111001011111111011001 #
b1000010010111001011111111011001 -
b1000001111101111111001101101000 "
b1000001111101111111001101101000 ,
b1001011 &
#1500
0$
#1510
1$
#1513
b100110 %
b1001100 &
#1520
0$
#1530
1$
#1533
b1000100000111110101101011011110 !
b1000100000111110101101011011110 3
b111110101101011011110 0
b0 4
b10000101 9
b11000 F
b10011 A
b100011100011111111 7
b1101 ;
b110 C
b10011 @
b11100 2
b1111 <
b100 B
1?
1>
1=
b101110 D
b101011 5
b11 E
b10000010 :
b10001000 1
b10011111010110101101110110110111101000011001001 6
b10001111011001000101 8
b1000010100011100011111111011111 #
b1000010100011100011111111011111 -
b1000001000011110110010001010111 "
b1000001000011110110010001010111 ,
b1001101 &
#1540
0$
#1550
1$
#1553
b100111 %
b1001110 &
#1560
0$
#1570
1$
#1573
b11000100001111000011010100111100 !
b11000100001111000011010100111100 3
1.
b1111000011010100111100 0
b11000 F
b10101 A
b10100110010000011000001 7
b10100 ;
b1 C
b10100 @
b100110 2
b10010 <
b10 B
1?
1>
1=
b101110 D
b101101 5
b1 E
b10111100001101010011101111100001111100010111010 6
b1001000011100110100111 8
b1000010101001100100000110000010 #
b1000010101001100100000110000010 -
b11000001000100001110011010011101 "
b11000001000100001110011010011101 ,
b1001111 &
#1580
0$
#1590
1$
#1593
b101000 %
b1010000 &
#1600
0$
#1610
1$
#1613
0.
b1000100111011000111100011111111 !
b1000100111011000111100011111111 3
b11011000111100011111111 0
b11000 F
b10011 A
b1000101000110001111101 7
b10001 ;
b10 C
b10100 @
b100010 2
b10001 <
b11 B
1?
1>
1=
b101110 D
b101100 5
b10 E
b10000011 :
b10001001 1
b11101100011110001111111010100100100111001010100 6
b110110110000011011111 8
b1000010100010100011000111110100 #
b1000010100010100011000111110100 -
b1000001110110110000011011111001 "
b1000001110110110000011011111001 ,
b1010001 &
#1620
0$
#1630
1$
#1633
b101001 %
b1010010 &
#1640
0$
#1650
1$
